madml/__init__.py
madml/assess.py
madml/calculators.py
madml/datasets.py
madml/models.py
madml/plots.py
madml/selectors.py
madml/splitters.py
madml/utils.py
madml/data/Dataset_Perovskite_Opband_simplified.xlsx
madml/data/Dataset_electromigration.xlsx
madml/data/Perovskite_stability_Wei_updated_forGlenn.xlsx
madml/data/Supercon_data_features_selected.xlsx
madml/data/citrine_thermal_conductivity_simplified.xlsx
madml/data/dielectric_constant_simplified.xlsx
madml/data/diffusion.csv
madml/data/double_perovskites_gap.xlsx
madml/data/elastic_tensor_2015_simplified.xlsx
madml/data/fluence.csv
madml/data/heusler_magnetic_simplified.xlsx
madml/data/perovskite_workfunctions_AO_simplified.xlsx
madml/data/piezoelectric_tensor.xlsx
madml/data/steel_strength.csv
madml/data/super_cond.csv
madml/hosting/__init__.py
madml/hosting/docker.py
madml/templates/docker/Dockerfile
madml/templates/docker/model_predict.py
madml/templates/docker/user_predict.ipynb
madml/templates/docker/user_predict.py
madml-2.6.7.dist-info/LICENSE
madml-2.6.7.dist-info/METADATA
madml-2.6.7.dist-info/WHEEL
madml-2.6.7.dist-info/top_level.txt
madml-2.6.7.dist-info/RECORD
