Metadata-Version: 2.1
Name: madml
Version: 2.6.7
Summary: Application domain of machine learning in materials science.
Home-page: https://github.com/leschultz/materials_application_domain_machine_learning.git
Author: Lane E. Schultz
Author-email: laneenriqueschultz@gmail.com
Classifier: Programming Language :: Python :: 3
Classifier: License :: OSI Approved :: MIT License
Classifier: Operating System :: OS Independent
Requires-Python: >=3.6
License-File: LICENSE
Requires-Dist: matplotlib
Requires-Dist: scipy
Requires-Dist: scikit-learn
Requires-Dist: pandas
Requires-Dist: numpy
Requires-Dist: pathos
Requires-Dist: tqdm
Requires-Dist: pytest
Requires-Dist: openpyxl
Requires-Dist: docker
Requires-Dist: tensorflow
Requires-Dist: udocker
Requires-Dist: scikeras
Requires-Dist: shap
Requires-Dist: kneed
